ShenduXuexiPythonJiaochengShiyongKerasPythonTheanoHeTensorflowKaifaShenduXuexiMoxing/README.md
ShenduXuexiPythonJiaochengShiyongKerasPythonTheanoHeTensorflowKaifaShenduXuexiMoxing/__init__.py
ShenduXuexiPythonJiaochengShiyongKerasPythonTheanoHeTensorflowKaifaShenduXuexiMoxing/__main__.py
ShenduXuexiPythonJiaochengShiyongKerasPythonTheanoHeTensorflowKaifaShenduXuexiMoxing/file.epub
ShenduXuexiPythonJiaochengShiyongKerasPythonTheanoHeTensorflowKaifaShenduXuexiMoxing/index.html
ShenduXuexiPythonJiaochengShiyongKerasPythonTheanoHeTensorflowKaifaShenduXuexiMoxing/css/__init__.py
ShenduXuexiPythonJiaochengShiyongKerasPythonTheanoHeTensorflowKaifaShenduXuexiMoxing/css/annotations.css
ShenduXuexiPythonJiaochengShiyongKerasPythonTheanoHeTensorflowKaifaShenduXuexiMoxing/css/main.css
ShenduXuexiPythonJiaochengShiyongKerasPythonTheanoHeTensorflowKaifaShenduXuexiMoxing/css/normalize.css
ShenduXuexiPythonJiaochengShiyongKerasPythonTheanoHeTensorflowKaifaShenduXuexiMoxing/css/popup.css
ShenduXuexiPythonJiaochengShiyongKerasPythonTheanoHeTensorflowKaifaShenduXuexiMoxing/font/__init__.py
ShenduXuexiPythonJiaochengShiyongKerasPythonTheanoHeTensorflowKaifaShenduXuexiMoxing/font/fontello.eot
ShenduXuexiPythonJiaochengShiyongKerasPythonTheanoHeTensorflowKaifaShenduXuexiMoxing/font/fontello.svg
ShenduXuexiPythonJiaochengShiyongKerasPythonTheanoHeTensorflowKaifaShenduXuexiMoxing/font/fontello.ttf
ShenduXuexiPythonJiaochengShiyongKerasPythonTheanoHeTensorflowKaifaShenduXuexiMoxing/font/fontello.woff
ShenduXuexiPythonJiaochengShiyongKerasPythonTheanoHeTensorflowKaifaShenduXuexiMoxing/img/__init__.py
ShenduXuexiPythonJiaochengShiyongKerasPythonTheanoHeTensorflowKaifaShenduXuexiMoxing/img/annotator-glyph-sprite.png
ShenduXuexiPythonJiaochengShiyongKerasPythonTheanoHeTensorflowKaifaShenduXuexiMoxing/img/annotator-icon-sprite.png
ShenduXuexiPythonJiaochengShiyongKerasPythonTheanoHeTensorflowKaifaShenduXuexiMoxing/img/apple-touch-icon.png
shendu_xuexi_python_jiaocheng_shiyong_keras_python_theano_he_tensorflow_kaifa_shendu_xuexi_moxing-2024.3.3.0.dist-info/METADATA
shendu_xuexi_python_jiaocheng_shiyong_keras_python_theano_he_tensorflow_kaifa_shendu_xuexi_moxing-2024.3.3.0.dist-info/WHEEL
shendu_xuexi_python_jiaocheng_shiyong_keras_python_theano_he_tensorflow_kaifa_shendu_xuexi_moxing-2024.3.3.0.dist-info/entry_points.txt
shendu_xuexi_python_jiaocheng_shiyong_keras_python_theano_he_tensorflow_kaifa_shendu_xuexi_moxing-2024.3.3.0.dist-info/top_level.txt
shendu_xuexi_python_jiaocheng_shiyong_keras_python_theano_he_tensorflow_kaifa_shendu_xuexi_moxing-2024.3.3.0.dist-info/RECORD
